mongoexe/__init__.py
mongoexe/cmd.py
mongoexe/mon.py
mroylib/__init__.py
mroylib/api.py
mroylib/auth.py
mroylib/cmd.py
mroylib/config.py
mroylib/science/__init__.py
mroylib/servers/__init__.py
mroylib/servers/tornado.py
mroylib/servers/res/bootstrap/dist/css/bootstrap-theme.css
mroylib/servers/res/bootstrap/dist/css/bootstrap-theme.css.map
mroylib/servers/res/bootstrap/dist/css/bootstrap-theme.min.css
mroylib/servers/res/bootstrap/dist/css/bootstrap.css
mroylib/servers/res/bootstrap/dist/css/bootstrap.css.map
mroylib/servers/res/bootstrap/dist/css/bootstrap.min.css
mroylib/servers/res/bootstrap/dist/js/bootstrap.js
mroylib/servers/res/bootstrap/dist/js/bootstrap.min.js
mroylib/servers/res/bootstrap/grunt/bs-glyphicons-data-generator.js
mroylib/servers/res/bootstrap/grunt/bs-lessdoc-parser.js
mroylib/servers/res/bootstrap/grunt/bs-raw-files-generator.js
mroylib/servers/res/bootstrap/grunt/sauce_browsers.yml
mroylib/servers/res/bootstrap/js/affix.js
mroylib/servers/res/bootstrap/js/alert.js
mroylib/servers/res/bootstrap/js/button.js
mroylib/servers/res/bootstrap/js/carousel.js
mroylib/servers/res/bootstrap/js/collapse.js
mroylib/servers/res/bootstrap/js/dropdown.js
mroylib/servers/res/bootstrap/js/modal.js
mroylib/servers/res/bootstrap/js/popover.js
mroylib/servers/res/bootstrap/js/scrollspy.js
mroylib/servers/res/bootstrap/js/tab.js
mroylib/servers/res/bootstrap/js/tooltip.js
mroylib/servers/res/bootstrap/js/transition.js
mroylib/servers/res/bootstrap/less/alerts.less
mroylib/servers/res/bootstrap/less/badges.less
mroylib/servers/res/bootstrap/less/bootstrap.less
mroylib/servers/res/bootstrap/less/breadcrumbs.less
mroylib/servers/res/bootstrap/less/button-groups.less
mroylib/servers/res/bootstrap/less/buttons.less
mroylib/servers/res/bootstrap/less/carousel.less
mroylib/servers/res/bootstrap/less/close.less
mroylib/servers/res/bootstrap/less/code.less
mroylib/servers/res/bootstrap/less/component-animations.less
mroylib/servers/res/bootstrap/less/dropdowns.less
mroylib_min-2.0.6.dist-info/METADATA
mroylib_min-2.0.6.dist-info/WHEEL
mroylib_min-2.0.6.dist-info/entry_points.txt
mroylib_min-2.0.6.dist-info/top_level.txt
mroylib_min-2.0.6.dist-info/RECORD
