Metadata-Version: 2.1
Name: mroylib-min
Version: 2.0.6
Summary: some libs
Home-page: https://github.com/Qingluan/.git
Author: Qing luan
Author-email: darkhackdevil@gmail.com
License: MIT
Platform: UNKNOWN
Requires-Dist: tornado
Requires-Dist: tabulate
Requires-Dist: redis
Requires-Dist: pymysql
Requires-Dist: pymongo
Requires-Dist: xlrd
Requires-Dist: xlwt
Requires-Dist: bs4
Requires-Dist: requests
Requires-Dist: termcolor
Requires-Dist: simplejson
Requires-Dist: pysocks
Requires-Dist: telethon
